{
    "data": [
        {
            "component": "mob-spacer",
            "props": {
                "style": "small",
                "id": "start",
                "label": "Overview"
            }
        },
        {
            "component": "mob-title",
            "props": {
                "tag": "h1",
                "isBold": true
            },
            "content": "mobJs"
        },
        {
            "component": "mob-title",
            "props": {
                "tag": "h4"
            },
            "content": "dependency:"
        },
        {
            "component": "mob-paragraph",
            "props": {
                "style": "medium"
            },
            "content": "<a href='/#mobCore_overview'>mobCore</a>, The mobMotion and mobCore folders must be at the same level."
        },
        {
            "component": "mob-spacer",
            "props": {
                "style": "small"
            }
        },
        {
            "component": "mob-title",
            "props": {
                "tag": "h4"
            },
            "content": "Main features:"
        },
        {
            "component": "mob-list",
            "props": {
                "style": "medium",
                "items": [
                    "No virtual dom or code to compile.",
                    "Pure vanilla javascript.",
                    "JsDoc type checking",
                    "Parent/Child reactivity.",
                    "SPA ready.",
                    "Independent of the DOM, it only exposes APIs to manage the same.",
                    "Optional use of web component."
                ]
            }
        },
        {
            "component": "mob-spacer",
            "props": {
                "style": "small"
            }
        },
        {
            "component": "mob-title",
            "props": {
                "tag": "h4"
            },
            "content": "Explore:"
        },
        {
            "component": "mob-list",
            "props": {
                "tag": "h3",
                "items": [
                    "<a href='#mobJs_initialization'>initialization</a>",
                    "<a href='#mobJs_component'>Component structure</a>",
                    "<a href='/#mobJs_web_component'>Web component</a>",
                    "<a href='/#mobJs_routing'>Routing</a>",
                    "<a href='/#mobJs_refs'>Refs</a>",
                    "<a href='/#mobJs_slot'>Slot</a>",
                    "<a href='/#mobJs_runtime'>Runtime add/remove</a>",
                    "<a href='/#mobJs_instanceName'>InstanceName</a>",
                    "<a href='/#mobJs_utils'>Utils</a>",
                    "<a href='/#mobJs_debug'>Debug</a>"
                ]
            }
        }
    ]
}
